<?xml version='1.0'  encoding='UTF-8' ?>
<history>
	<historyItem>
		<sql><![CDATA[begin

update safe_kiosk_print
set printed_date_time = sysdate
where booking_reference = :booking_reference
and collection_point_code = :collection_point_code
and job_number = :job_number;

update ca_booked_person
set printed_date_time = sysdate
where booking_reference = :booking_reference
and collection_point_code = :collection_point_code;

:success := 'true';

end;]]></sql>
		<connection><![CDATA[Trunk]]></connection>
		<timestamp><![CDATA[1721813693085]]></timestamp>
		<type><![CDATA[SQL]]></type>
		<executed><![CDATA[1]]></executed>
		<execTime><![CDATA[0.317]]></execTime>
	</historyItem>
</history>
