<?xml version='1.0'  encoding='UTF-8' ?>
<history>
	<historyItem>
		<sql><![CDATA[drop index ca_person_detail_dw1;
    drop index ca_person_detail_dw2;
    drop index ca_person_detail_dw3;
    drop index ca_person_detail_dw4;
    drop index ca_person_detail_dw5;
    drop index ca_person_detail_dw6;
    drop index ca_person_detail_dw7;
    drop index ca_person_detail_dw8;
    drop index ca_person_detail_dw9;
    drop index ca_person_detail_dw11;
    drop index ca_person_detail_dw12;
    drop index ca_person_detail_dw13;
    drop index ca_person_detail_dw14;
    drop index ca_person_detail_dw15;
    drop index ca_person_detail_dw16;

    drop index ca_active_host_location_person_dw1;
    drop index ca_active_host_location_person_dw2;
    drop index ca_active_host_location_person_dw3;
    drop index ca_active_host_location_person_dw4;
    drop index ca_active_host_location_person_dw5;
    drop index ca_active_host_location_person_dw6;
    drop index ca_active_host_location_person_dw7;

create index ca_active_host_location_person_mv14 on ca_active_host_location_person(forename_lower) indextype is ctxsys.context;

create index ca_active_host_location_person_mv15 on ca_active_host_location_person(surname_lower) indextype is ctxsys.context;]]></sql>
		<connection><![CDATA[Dev]]></connection>
		<timestamp><![CDATA[1716817101981]]></timestamp>
		<type><![CDATA[Script]]></type>
		<executed><![CDATA[1]]></executed>
		<execTime><![CDATA[3.073]]></execTime>
	</historyItem>
</history>
